{
    "BatmanLogo.stl": {
        "hash": "1a0f6daf61cf868f4ac7b4335cec4575c5c21df3"
    },
    "BatmanLogo_0.2mm_PET_MK3.gcode": {
        "hash": "847acec07fb9c269f3ab8b3d079ebf75eedf48c4",
        "analysis": {
            "analysisPending": false,
            "progress": [
                [
                    0,
                    4730.0
                ],
                [
                    0.0005985577663451307,
                    4740.0
                ],
                [
                    0.006316818369098613,
                    4680.0
                ],
                [
                    0.014764037487149894,
                    4620.0
                ],
                [
                    0.01824090264835661,
                    4560.0
                ],
                [
                    0.020855960850835336,
                    4500.0
                ],
                [
                    0.023261814397115766,
                    4440.0
                ],
                [
                    0.026025059231068286,
                    4380.0
                ],
                [
                    0.032722513849638805,
                    4320.0
                ],
                [
                    0.03860116468881098,
                    4260.0
                ],
                [
                    0.04836230527259657,
                    4200.0
                ],
                [
                    0.057933999417713704,
                    4140.0
                ],
                [
                    0.06739353662214675,
                    4080.0
                ],
                [
                    0.07819895711478884,
                    4020.0
                ],
                [
                    0.08935711990274307,
                    3960.0
                ],
                [
                    0.0983901120581496,
                    3900.0
                ],
                [
                    0.10960813062273833,
                    3840.0
                ],
                [
                    0.12233823395240478,
                    3780.0
                ],
                [
                    0.13123117521296743,
                    3720.0
                ],
                [
                    0.14086795525112403,
                    3660.0
                ],
                [
                    0.15227077126202127,
                    3600.0
                ],
                [
                    0.1626461599613669,
                    3540.0
                ],
                [
                    0.17240613829706247,
                    3480.0
                ],
                [
                    0.18360381752007637,
                    3420.0
                ],
                [
                    0.19731253374151486,
                    3360.0
                ],
                [
                    0.21604506733193748,
                    3300.0
                ],
                [
                    0.23098344203258594,
                    3240.0
                ],
                [
                    0.24769133945024502,
                    3180.0
                ],
                [
                    0.26442829307015386,
                    3120.0
                ],
                [
                    0.28010353305985636,
                    3060.0
                ],
                [
                    0.2976528980946686,
                    3000.0
                ],
                [
                    0.3115185178082558,
                    2940.0
                ],
                [
                    0.3309745508346975,
                    2880.0
                ],
                [
                    0.3447082553900708,
                    2820.0
                ],
                [
                    0.3628503669507782,
                    2760.0
                ],
                [
                    0.37787707250626595,
                    2700.0
                ],
                [
                    0.39434787131356697,
                    2640.0
                ],
                [
                    0.411557859906102,
                    2580.0
                ],
                [
                    0.42653110204945016,
                    2520.0
                ],
                [
                    0.4445110800016039,
                    2460.0
                ],
                [
                    0.4578269563686256,
                    2400.0
                ],
                [
                    0.4776624633964492,
                    2340.0
                ],
                [
                    0.49169893357926503,
                    2280.0
                ],
                [
                    0.5093529009421764,
                    2220.0
                ],
                [
                    0.5247381600334262,
                    2160.0
                ],
                [
                    0.5412200001975822,
                    2100.0
                ],
                [
                    0.558460207240457,
                    2040.0
                ],
                [
                    0.572952859798594,
                    1980.0
                ],
                [
                    0.5914192385764088,
                    1920.0
                ],
                [
                    0.6049780247942385,
                    1860.0
                ],
                [
                    0.6241475636664976,
                    1800.0
                ],
                [
                    0.6386686913028394,
                    1740.0
                ],
                [
                    0.6559908368360585,
                    1680.0
                ],
                [
                    0.6720966897431025,
                    1620.0
                ],
                [
                    0.688257168310376,
                    1560.0
                ],
                [
                    0.7062115768045499,
                    1500.0
                ],
                [
                    0.7206658751757173,
                    1440.0
                ],
                [
                    0.7402439442516081,
                    1380.0
                ],
                [
                    0.7538492203930375,
                    1320.0
                ],
                [
                    0.7856494903832687,
                    1260.0
                ],
                [
                    0.8034022488338293,
                    1200.0
                ],
                [
                    0.8185143796239314,
                    1140.0
                ],
                [
                    0.8242460060797198,
                    1080.0
                ],
                [
                    0.8278449072903755,
                    1020.0
                ],
                [
                    0.8372103023995193,
                    960.0
                ],
                [
                    0.848436456700738,
                    900.0
                ],
                [
                    0.8607760446721676,
                    840.0
                ],
                [
                    0.8732243028400113,
                    780.0
                ],
                [
                    0.8831946480799953,
                    720.0
                ],
                [
                    0.8932509996786384,
                    660.0
                ],
                [
                    0.9044225283196275,
                    600.0
                ],
                [
                    0.9133764876049146,
                    540.0
                ],
                [
                    0.92439750511825,
                    480.0
                ],
                [
                    0.9376500389643673,
                    420.0
                ],
                [
                    0.9478725920398791,
                    360.0
                ],
                [
                    0.9586576731909463,
                    300.0
                ],
                [
                    0.9712605103547588,
                    240.0
                ],
                [
                    0.978121841954018,
                    180.0
                ],
                [
                    0.9866184566158939,
                    120.0
                ],
                [
                    0.9930398773130916,
                    60.0
                ],
                [
                    1,
                    0
                ]
            ],
            "estimatedPrintTime": 4730.0,
            "firstFilament": 0.0005985577663451307
        }
    }
}